lugus/__about__.py
lugus/__init__.py
lugus/entry_points.py
lugus/lugus.py
lugus/style.tcss
lugus-0.2.4.dist-info/METADATA
lugus-0.2.4.dist-info/WHEEL
lugus-0.2.4.dist-info/entry_points.txt
lugus-0.2.4.dist-info/licenses/LICENSE.txt
lugus-0.2.4.dist-info/RECORD
