Metadata-Version: 2.3
Name: lugus
Version: 0.2.4
Summary: Terminal Feeds Reader
Project-URL: Documentation, https://github.com/OpenCode/lugus#readme
Project-URL: Issues, https://github.com/OpenCode/lugus/issues
Project-URL: Source, https://github.com/OpenCode/lugus
Author-email: Francesco Apruzzese <cescoap@gmail.com>
License: MIT
Classifier: Development Status :: 4 - Beta
Classifier: Programming Language :: Python
Classifier: Programming Language :: Python :: 3.8
Classifier: Programming Language :: Python :: 3.9
Classifier: Programming Language :: Python :: 3.10
Classifier: Programming Language :: Python :: 3.11
Classifier: Programming Language :: Python :: 3.12
Classifier: Programming Language :: Python :: Implementation :: CPython
Classifier: Programming Language :: Python :: Implementation :: PyPy
Requires-Python: >=3.8
Requires-Dist: feedparser==6.0.11
Requires-Dist: markdownify==0.13.1
Requires-Dist: textual==0.86.0
